topsis/__init__.py
topsis/topsis.py
topsis_varun_102217105-0.2.0.dist-info/LICENSE
topsis_varun_102217105-0.2.0.dist-info/METADATA
topsis_varun_102217105-0.2.0.dist-info/WHEEL
topsis_varun_102217105-0.2.0.dist-info/entry_points.txt
topsis_varun_102217105-0.2.0.dist-info/top_level.txt
topsis_varun_102217105-0.2.0.dist-info/RECORD
